[
    {
        "productId": 20001, 
        "brand": "HP", 
        "img_1":"image/product/20001_1.png",
        "img_2":"image/product/20001_2.png",
        "img_3":"image/product/20001_3.png",
        "img_4":"image/product/20001_4.png",
        "img_5":"image/product/20001_5.png",
        "img_6":"image/product/20001_6.png",
        "name": "Laptop HP Pavilion 15 EG2063TU 6K791PA",
        "CPU": "Intel Core i3-1215U 1.2GHz up to 4.4GHz 10MB",
        "RAM":"8GB (4x2) DDR4 3200MHz (2x SO-DIMM socket, up to 16GB SDRAM)", 
        "Hardware": "256 GB PCIe NVMe M.2 SSD (1 slot)",
        "Card":"Intel UHD Graphics",
        "screen":"15.6 inch FHD (1920 x 1080) IPS, micro-edge, BrightView, 250 nits, 45% NTSC",
        "CGT": "1x SuperSpeed USB Type-C 10Gbps signaling rate (USB Power Delivery, DisplayPort 1.4, HP Sleep and Charge)/2x SuperSpeed USB Type-A 5Gbps signaling rate/1x HDMI 2.1/1x headphone/microphone combo/1x AC smart pin",
        "keyboard":"Không LED",
        "SDcard":"None",
        "Audio":"B&O, Dual Speakers, HP Audio Boost",
        "Bluetooth":"v5.2",        
        "Webcam":"HP Wide Vision 720p HD camera with temporal noise reduction and integrated dual array digital microphones",
        "OS":"Windows 11 Home",
        "Pin":"3 Cell 43WHr",
        "Weigth":"1.74 kg",
        "color":"Natural Silver",
        "size":"36.02 x 23.4 x 1.79 cm",
        "description_1":"Đánh giá chi tiết laptop HP Pavilion 15 EG2063TU 6K791PA/Laptop HP Pavilion 15 EG2063TU 6K791PA là một chiếc laptop mỏng nhẹ, phổ thông mang vẻ đẹp hút mắt và tạo ấn tượng đối với khách hàng như học sinh - sinh viên, nhân viên văn phòng.",
        "description_2":"Thiết kế trang nhã/Thiết kế trên từng chi tiết của HP Pavilion 15 EG2063TU 6K791PA được trau chuốt và sắp đặt kĩ càng nhằm bộc lộ hết vẻ đẹp hiện đại và thời thượng của chiếc máy. Khoác lên vỏ lớp màu Natural Silver sang trọng cùng viền màn hình được thiết kế siêu mỏng, càng thể hiện được nét đẹp thanh thoát và trang nhã của sản phẩm.",
        "description_3":"Hiệu năng bền bỉ và mượt mà/HP Pavilion 15 EG2063TU 6K791PA nhận được sự cân bằng hài hòa giữa hiệu năng cũng như ngoại hình bóng nhoáng. Không chỉ sở hữu thiết kế đẹp, ấn tượng mà mẫu laptop HP Pavilion 15 có thể đáp ứng được nhu cầu sử dụng từ làm việc đến giải trí./Được trang bị CPU gen 12th cực kỳ mạnh mẽ, sẽ không để bạn chờ đợi lâu khi xử lý các tiến trình nhanh gọn và mượt mà. Kết hợp với bộ nhớ RAM 8GB chuẩn DDR4, ổ cứng 512GB PCIe NVMe SSD đảm bảo quá trình xử lý các tác vụ, truy xuất luôn diễn ra mượt mà và tốc độ.",
        "description_4":"Bản lề nâng đỡ hỗ trợ tiện lợi/Đặc biệt, HP khá tinh tế trong việc đem đến trải nghiệm tốt nhất cho người dùng với trang bị tiện lợi hơn. Điển hình là nhiều chi tiết nhỏ nhưng mang lại giá trị cao, cho phép người dùng làm việc thuận tiện hơn. Ví dụ như bản lề nâng hỗ trợ tư thế gõ phím tự nhiên của HP Pavilion 15. Bên cạnh đó cũng giúp máy có thể tản nhiệt tốt hơn trong quá trình sử dụng lâu dài.",
        "description_5":"Màn hình sắc nét/Màn hình của HP Pavilion 15 EG2063TU 6K791PA có kích thước 15.6 inch với độ phân giải Full HD (1920 x 1080) cùng tấm nền IPS giúp hình ảnh và màu sắc hiển thị vô cùng sắc nét, chân thực và sống động. Laptop HP Pavilion 15 mang thiết kế nhỏ gọn, tối giản với đường nét góc cạnh tỉ mỉ và tinh tế cho góc nhìn rộng hơn.",
        "description_6":"Công nghệ sạc nhanh tiên tiến/HP Pavilion 15 được trang bị công nghệ tấm nền hiện đại và công nghệ sạc pin nhanh 90% chỉ trong vòng 90 phút sạc. Điều này giúp tăng tính cơ động cho máy, giúp bạn có thể thoải mái sử dụng máy cả ngày dài ở bất cứ nơi nào với viên pin tích hợp mà không cần đến nguồn sạc hay lo lắng đến vấn đề sạc pin.",
        "old-price": 14990000,
        "new-price":13990000
    },
    {
        "productId": 20002, 
        "brand": "HP", 
        "img_1":"image/product/20002_1.png",
        "img_2":"image/product/20002_2.png",
        "img_3":"image/product/20002_3.png",
        "img_4":"image/product/20002_4.png",
        "img_5":"image/product/20002_5.png",
        "img_6":"image/product/20002_6.png",
        "name": "Laptop HP Pavilion 15 EG0513TU 46M12PA",
        "CPU": "Intel Core i3-1125G4 2.0GHz up to 3.7GHz 8MB",
        "RAM":"4GB (4GBx1) DDR4 3200MHz (2x SO-DIMM socket, up to 16GB SDRAM)", 
        "Hardware": "256GB PCIe NVMe M.2 SSD",
        "Card":"Intel UHD Graphics",
        "screen":"15.6 inch FHD (1920 x 1080) IPS, micro-edge, BrightView, 250 nits, 45% NTSC",
        "CGT": "1x SuperSpeed USB Type-C® 10Gbps signaling rate (USB Power Delivery, DisplayPort™ 1.4, HP Sleep and Charge)/2x SuperSpeed USB Type-A 5Gbps signaling rate/1x HDMI 2.0/1x AC smart pin/1x headphone&microphone combo",
        "keyboard":"Không có led",
        "SDcard":"multi-format SD media card reader",
        "Audio":"B&O, Dual Speakers, HP Audio Boost",
        "Bluetooth":"v5.0",        
        "Webcam":"HP Wide Vision HD Camera",
        "OS":"Windows 11",
        "Pin":"3 Cell 41WHr",
        "Weigth":"1.75 kg",
        "color":"Vàng",
        "size":"36.02 x 23.4 x 1.79 cm",
        "description_1":"Đánh giá chi tiết laptop HP Pavilion 15 EG0513TU 46M12PA/Laptop HP Pavilion 15 EG0513TU 46M12PA là mẫu laptop cho sinh viên, nhân viên văn phòng tầm trung rất được chú ý bởi thiết kế và hiệu năng mạnh mẽ của mình.",
        "description_2":"Thiết kế mỏng nhẹ, sang trọng, đẹp mắt/Laptop HP Pavilion 15 EG0513TU 46M12PA có kích thước màn hình 15.6 inch, độ dày chỉ 17.9 mm và cân nặng 1.75 kg. Với kích thước mỏng nhẹ này bạn hoàn toàn có thể cầm máy bằng 1 tay dễ dàng, phù hợp với những ai thường xuyên thay đổi vị trí làm việc./Máy được thiết kế với phong cách tối giản màu vàng nhạt, với logo HP sáng bóng đính giữa trung tâm mặt A (mặt trên) tạo điểm nhấn ấn tượng cho HP Pavilion 15 EG0513TU 46M12PA.",
        "description_3":"Cấu hình tối ưu hóa cho công việc/Là mẫu laptop giá rẻ, laptop HP Pavilion 15 EG0513TU 46M12PA được trang bị CPU Intel Core i3-1125G4, card đồ họa Intel UHD Graphics khá khiêm tốn. Tuy nhiên với mức cấu hình trên cũng đủ để bạn thỏa mãn các tác vụ văn phòng và giải trí cơ bản./Bên cạnh đó với tựa game cơ bản như Liên Minh Huyền Thoại và Fifa Online 4, Dota 2,… cũng không thể làm khó được mẫu laptop HP giá rẻ này.",
        "description_4":"Màn hình IPS Full HD/Màn hình 15.6 inch FHD (1920 x 1080) IPS, micro-edge, BrightView, 250 nits, 45% NTSC được trang bị trên laptop HP Pavilion 15 EG0513TU 46M12PA. Với độ phủ màu ở mức khá và độ sáng ở mức 250 nits đảm bảo chất lượng hình ảnh sống động, sắc nét, thỏa mãn nhu cầu giải trí cơ bản của người dùng.",
        "description_5":"Bàn phím cứng cáp, độ nảy cao/Bàn phím của HP Pavilion 15 EG0513TU 46M12PA có thiết kế khá dày, cứng chắc, độ lún thấp và độ nảy cao giúp tạo cảm giác gõ phím nhanh hơn và chính xác hơn. Phần bàn phím chính và phím số phụ có kích thước khá lớn, phù hợp với những ai thường xuyên soạn thảo văn bản./Với những gì mà mình sở hữu, laptop HP Pavilion 15 EG0513TU 46M12PA chắc chắn là mẫu laptop văn phòng bạn không nên bỏ qua.",
        "description_6":"",
        "old-price": 14190000,
        "new-price":13990000
    },
    {
        "productId": 20003, 
        "brand": "HP", 
        "img_1":"image/product/20003_1.png",
        "img_2":"image/product/20003_2.png",
        "img_3":"image/product/20003_3.png",
        "img_4":"image/product/20003_4.png",
        "img_5":"image/product/20003_5.png",
        "img_6":"image/product/20003_6.png",
        "name": "Laptop HP 14s DQ5053TU 6R9M6PA",
        "CPU": "Intel Core i5-1235U (up to 4.4 GHz, 12 MB cache, 10 cores, 12 threads)",
        "RAM":"8 GB DDR4-3200 MHz RAM (2 x 4 GB)", 
        "Hardware": "512 GB PCIe® NVMe™ M.2 SSD",
        "Card":"Intel Iris Xe Graphics",
        "screen":"14 inch, HD (1366 x 768), micro-edge, BrightView, 250 nits, 45% NTSC",
        "CGT": "1 x SuperSpeed USB Type-C® 5Gbps signaling rate/2 x SuperSpeed USB Type-A 5Gbps signaling rate/1 x HDMI 1.4b/1x headphone&microphone combo/1 x AC smart pin",
        "keyboard":"Không led",
        "SDcard":"1 multi-format SD media card reader",
        "Audio":"Dual speakers",
        "Bluetooth":"Bluetooth® 5",        
        "Webcam":"HP True Vision 720p HD camera with temporal noise reduction and integrated dual array digital microphones",
        "OS":"Windows 11 Home",
        "Pin":"3 Cell 41Whr",
        "Weigth":"1.46 kg",
        "color":"Bạc",
        "size":"32.4 x 22.5 x 1.79 cm ",
        "description_1":"Đánh giá chi tiết HP 14s DQ5053TU 6R9M6PA/Laptop HP 14s DQ5053TU 6R9M6PA là một chiếc laptop văn phòng mang vẻ đẹp hút mắt và tạo ấn tượng đối với khách hàng. Thiết kế trong từng chi tiết máy tính đều được trau chuốt và sắp đặt kĩ lượng để bộc lộ hết vẻ đẹp hiện đại và thời thượng của laptop.",
        "description_2":"Thiết kế đẹp và tiện lợi/Laptop HP 14s khoác lên mình màu áo xám hiện đại và thanh lịch, một màu sắc nhẹ nhàng, tinh tế và năng động. Viền màn hình cũng được thiết kế siêu mỏng, sang trọng, càng thể hiện được nét đẹp thanh thoát của sản phẩm./Đặc biệt, HP còn rất tinh tế trong việc đem đến trải nghiệm tốt nhất cho người dùng. Nhiều chi tiết nhỏ được gia công tỉ mỉ nhưng mang lại giá trị sử dụng cao, cho phép người dùng làm việc thuận tiện hơn. Ví dụ như phần bản lề được nâng lên một góc thích hợp để bạn có thể gõ phím thoải mái hơn cũng như nâng cao khả năng tản nhiệt của laptop.",
        "description_3":"Hiệu năng HP 14s DQ5053TU 6R9M6PA bền bỉ và mượt mà/HP 14s DQ5053TU 6R9M6PA là một trong những mẫu laptop mỏng nhẹ sở hữu sức mạnh khủng hiện nay. Nó cho thấy được sự cân bằng và hài hòa giữa hiệu năng cũng như ngoại hình bên ngoài. Không chỉ sở hữu vẻ ngoài đẹp ấn tượng mà HP 14s còn có thể đáp ứng được nhu cầu sử dụng của nhiều đối tượng khách hàng từ học sinh, sinh viên đến nhân viên văn phòng./Được trang bị bộ vi xử lý thế hệ 12 mạnh mẽ, sẽ không để bạn chờ đợi lâu khi xử lý các tác vụ. Kết hợp với bộ nhớ RAM dung lượng 8GB chuẩn DDR4, ổ cứng 512GB PCIe NVMe SSD giúp xử lý các tác vụ một cách mượt mà và nhanh chóng, tăng tốc quá trình truy cập và đảm bảo sự ổn định khi sử dụng.",
        "description_4":"Khả năng hiển thị sống động/Laptop HP 14s DQ5053TU 6R9M6PA sở hữu kích thước màn hình 14 inch với độ phân giải HD (1366 x 768) cùng độ sáng màn hình 250nits mang lại hiển thị hình ảnh tốt cho công việc văn phòng và giải trí hằng ngày. Dải màu 45% NTSC được tái hiện một cách chân thật cho mọi trình chiếu qua màn hình sống động./Laptop HP 14s mang thiết kế nhỏ gọn, tối giản với đường nét góc cạnh tỉ mỉ và tinh tế. Trọng lượng thiết bị được tối ưu hoá chỉ 1,46kg để người dùng có thể linh hoạt hơn trong việc mang xách, di chuyển đến bất kỳ đâu.",
        "description_5":"Cổng kết nối đa dạng/HP 14s DQ5053TU 6R9M6PA còn được trang bị các cổng kết nối thông dụng. Bao gồm hỗ trợ USB Type-C, USB Type-A, HDMI và jack cắm 3.5mm để thuận tiện cho việc kết nối các thiết bị ngoại vi như chuột không dây, bàn phím cơ hoặc tai nghe hỗ trợ công việc và nhu cầu giải trí.",
        "description_6":"",
        "old-price":18990000,
        "new-price":16490000
    },
    {
        "productId": 20004, 
        "brand": "HP", 
        "img_1":"image/product/20004_1.png",
        "img_2":"image/product/20004_2.png",
        "img_3":"image/product/20004_3.png",
        "img_4":"image/product/20004_4.png",
        "img_5":"image/product/20004_5.png",
        "img_6":"image/product/20004_6.png",
        "name": "Laptop HP Pavilion 14 dv2036TU 6K772PA",
        "CPU": "Intel Core i5-1235U 1.3GHz up to 4.4GHz 12MB",
        "RAM":"8GB (4x2) DDR4 3200MHz (2x SO-DIMM socket, up to 16GB SDRAM)", 
        "Hardware": "256 GB PCIe NVMe M.2 SSD (1 slot)",
        "Card":"Intel Iris Xe Graphics",
        "screen":"14 inch FHD (1920 x 1080) IPS, micro-edge, BrightView, 250 nits, 45% NTSC",
        "CGT": "1x SuperSpeed USB Type 10Gbps signaling rate (USB Power Delivery, DisplayPort 1.4, HP Sleep and Charge)/2x SuperSpeed USB Type-A 5Gbps signaling rate/1x HDMI 2.1/1x headphone&microphone combo/1 x AC smart pin",
        "keyboard":"",
        "SDcard":"none",
        "Audio":"B&O PLAY; HP Audio Boost; Dual speakers",
        "Bluetooth":"v5.2",        
        "Webcam":"HP Wide Vision 720p HD camera with temporal noise reduction and integrated dual array digital microphones",
        "OS":"Windows 11 Home",
        "Pin":"3 Cell 43WHr",
        "Weigth":"1.41 kg",
        "color":"Natural Silver aluminum",
        "size":"32.5 x 21.66 x 1.7 cm",
        "description_1":"Đánh giá chi tiết HP Pavilion 14 dv2036TU 6K772PA/Laptop HP Pavilion 14 dv2036TU 6K772PA là một chiếc laptop văn phòng mang vẻ đẹp hút mắt và tạo ấn tượng đối với khách hàng. Thiết kế trong từng chi tiết máy tính đều được trau chuốt và sắp đặt kĩ lượng để bộc lộ hết vẻ đẹp hiện đại và thời thượng của laptop.",
        "description_2":"Thiết kế đẹp và tiện lợi/HP Pavilion 14 dv2036TU 6K772PA khoác lên mình màu áo xám hiện đại và thanh lịch, một màu sắc nhẹ nhàng, tinh tế và năng động. Viền màn hình cũng được thiết kế siêu mỏng, sang trọng, càng thể hiện được nét đẹp thanh thoát của sản phẩm./Đặc biệt, HP còn rất tinh tế trong việc đem đến trải nghiệm tốt nhất cho người dùng. Nhiều chi tiết nhỏ được gia công tỉ mỉ nhưng mang lại giá trị sử dụng cao, cho phép người dùng làm việc thuận tiện hơn. Ví dụ như phần bản lề được nâng lên một góc thích hợp để bạn có thể gõ phím thoải mái hơn cũng như nâng cao khả năng tản nhiệt của laptop.",
        "description_3":"Hiệu năng HP Pavilion 14 bền bỉ và mượt mà/HP Pavilion 14 dv2036TU 6K772PA là một trong những mẫu laptop mỏng nhẹ sở hữu sức mạnh khủng hiện nay. Nó cho thấy được sự cân bằng và hài hòa giữa hiệu năng cũng như ngoại hình bên ngoài. Không chỉ sở hữu vẻ ngoài đẹp ấn tượng mà HP Pavilion 14 còn có thể đáp ứng được nhu cầu sử dụng của nhiều đối tượng khách hàng từ học sinh, sinh viên đến nhân viên văn phòng./Được trang bị bộ vi xử lý thế hệ 12 mạnh mẽ, sẽ không để bạn chờ đợi lâu khi xử lý các tác vụ. Kết hợp với bộ nhớ RAM dung lượng 8GB chuẩn DDR4, ổ cứng 256GB PCIe NVMe SSD giúp xử lý các tác vụ một cách mượt mà và nhanh chóng, tăng tốc quá trình truy cập và đảm bảo sự ổn định khi sử dụng.",
        "description_4":"Dung lượng pin lớn và hỗ trợ sạc nhanh/HP Pavilion 14 được trang bị viên pin 43WHr, đủ lớn để bạn làm việc và học tập cả ngày dài. Hơn nữa, công nghệ sạc pin nhanh cho phép bạn đầy 90% trong vòng 90 phút. Điều này không những tăng tính cơ động cho máy, mà nó còn giúp bạn thoải mái sử dụng laptop ở bất cứ nơi nào.",
        "description_5":"Chất lượng âm thanh tuyệt vời/Chưa dừng lại ở đó khi HP Pavilion 14 dv2036TU 6K772PA cũng được trang bị hệ thống loa kép cùng công nghệ khuếch âm HP Audio Boost cùng âm thanh được tinh chỉnh bởi các chuyên gia của B&O PLAY./Sự kết hợp này đang đem đến cho người dùng trải nghiệm âm nhạc với chiều sâu chân thực và đầy sống động. Do đó, dù ở vị trí nào thì chất lượng âm thanh sẽ không bị ảnh hưởng hay khác biệt nhiều.",
        "description_6":"Khả năng hiển thị sống động/Sở hữu kích thước màn hình 14 inch với độ phân giải Full HD cùng tấm nền IPS giúp hình ảnh và màu sắc hiển thị vô cùng sắc nét, chân thực và sống động. Không gian hiển thị cũng được mở rộng hơn nhờ thiết kế tràn viền, nó mang đến hình ảnh sống động đến từng chi tiết nhỏ và mọi góc nhìn./Laptop HP Pavilion 14 mang thiết kế nhỏ gọn, tối giản với đường nét góc cạnh tỉ mỉ và tinh tế. Trọng lượng thiết bị được tối ưu hoá chỉ 1,4kg để người dùng có thể linh hoạt hơn trong việc mang xách, di chuyển đến bất kỳ đâu. ",
        "old-price":17990000,
        "new-price":16990000
    },
    {
        "productId": 20005, 
        "brand": "HP", 
        "img_1":"image/product/20005_1.png",
        "img_2":"image/product/20005_2.png",
        "img_3":"image/product/20005_3.png",
        "img_4":"image/product/20005_4.png",
        "img_5":"image/product/20005_5.png",
        "img_6":"image/product/20005_6.png",
        "name": "Laptop HP Pavilion 15 EG2036TX 6K782PA",
        "CPU": "Intel Core i5-1235U 1.3GHz up to 4.4GHz 12MB",
        "RAM":"8GB (4x2) DDR4 3200MHz (2x SO-DIMM socket, up to 16GB SDRAM)", 
        "Hardware": "512GB PCIe NVMe M.2 SSD (1 slot)",
        "Card":"NVIDIA GeForce MX550 2GB GDDR6 + Intel Iris Xe Graphics",
        "screen":"15.6 inch FHD (1920 x 1080) IPS, micro-edge, BrightView, 250 nits, 45% NTSC",
        "CGT": "1x SuperSpeed USB Type-C 10Gbps signaling rate (USB Power Delivery, DisplayPort 1.4, HP Sleep and Charge)/2x SuperSpeed USB Type-A 5Gbps signaling rate/1x HDMI 2.1/1x headphone&microphone combo/1 x AC smart pin",
        "keyboard":"Không LED",
        "SDcard":"none",
        "Audio":"B&O, Dual Speakers, HP Audio Boost",
        "Bluetooth":"v5.2",        
        "Webcam":"HP Wide Vision 720p HD camera with temporal noise reduction and integrated dual array digital microphones",
        "OS":"Windows 11 Home",
        "Pin":"3 Cell 43WHr",
        "Weigth":"1.74 kg",
        "color":"Natural Silver",
        "size":"36.02 x 23.4 x 1.79 cm",
        "description_1":"Đánh giá chi tiết laptop HP Pavilion 15 EG2036TX 6K782PA/Laptop HP Pavilion 15 EG2036TX 6K782PA là một chiếc laptop mỏng nhẹ, phổ thông mang vẻ đẹp hút mắt và tạo ấn tượng đối với khách hàng như học sinh - sinh viên, nhân viên văn phòng.",
        "description_2":"Thiết kế trang nhã/Thiết kế trên từng chi tiết của HP Pavilion 15 EG2036TX 6K782PA được trau chuốt và sắp đặt kĩ càng nhằm bộc lộ hết vẻ đẹp hiện đại và thời thượng của chiếc máy. Khoác lên vỏ lớp màu Natural Silver sang trọng cùng viền màn hình được thiết kế siêu mỏng, càng thể hiện được nét đẹp thanh thoát và trang nhã của sản phẩm.",
        "description_3":"Hiệu năng bền bỉ và mượt mà/HP Pavilion 15 EG2036TX 6K782PA nhận được sự cân bằng hài hòa giữa hiệu năng cũng như ngoại hình bóng nhoáng. Không chỉ sở hữu thiết kế đẹp, ấn tượng mà mẫu laptop HP Pavilion 15 có thể đáp ứng được nhu cầu sử dụng từ làm việc đến giải trí./Được trang bị CPU gen 12th cực kỳ mạnh mẽ, sẽ không để bạn chờ đợi lâu khi xử lý các tiến trình nhanh gọn và mượt mà. Kết hợp với bộ nhớ RAM 8GB chuẩn DDR4, ổ cứng 512GB PCIe NVMe SSD đảm bảo quá trình xử lý các tác vụ, truy xuất luôn diễn ra mượt mà và tốc độ.",
        "description_4":"Bản lề nâng đỡ hỗ trợ tiện lợi/Đặc biệt, HP khá tinh tế trong việc đem đến trải nghiệm tốt nhất cho người dùng với trang bị tiện lợi hơn. Điển hình là nhiều chi tiết nhỏ nhưng mang lại giá trị cao, cho phép người dùng làm việc thuận tiện hơn. Ví dụ như bản lề nâng hỗ trợ tư thế gõ phím tự nhiên của HP Pavilion 15. Bên cạnh đó cũng giúp máy có thể tản nhiệt tốt hơn trong quá trình sử dụng lâu dài.",
        "description_5":"Màn hình sắc nét/Màn hình của HP Pavilion 15 EG2036TX 6K782PA có kích thước 15.6 inch với độ phân giải Full HD (1920 x 1080) cùng tấm nền IPS giúp hình ảnh và màu sắc hiển thị vô cùng sắc nét, chân thực và sống động. Laptop HP Pavilion 15 mang thiết kế nhỏ gọn, tối giản với đường nét góc cạnh tỉ mỉ và tinh tế cho góc nhìn rộng hơn.",
        "description_6":"Công nghệ sạc nhanh tiên tiến/HP Pavilion 15 được trang bị công nghệ tấm nền hiện đại và công nghệ sạc pin nhanh 90% chỉ trong vòng 90 phút sạc. Điều này giúp tăng tính cơ động cho máy, giúp bạn có thể thoải mái sử dụng máy cả ngày dài ở bất cứ nơi nào với viên pin tích hợp mà không cần đến nguồn sạc hay lo lắng đến vấn đề sạc pin.",
        "old-price":20590000,
        "new-price":19490000
    },
    {
        "productId": 20006, 
        "brand": "HP", 
        "img_1":"image/product/20006_1.png",
        "img_2":"image/product/20006_2.png",
        "img_3":"image/product/20006_3.png",
        "img_4":"image/product/20006_4.png",
        "img_5":"image/product/20006_5.png",
        "img_6":"image/product/20006_6.png",
        "name": "Laptop HP Pavilion 15 EG0506TX 46M05PA",
        "CPU": "Intel Core i5-1135G7 2.4GHz up to 4.2GHz 8MB",
        "RAM":"8GB (4GBx2) DDR4 3200MHz (2x SO-DIMM socket, up to 16GB SDRAM)", 
        "Hardware": "512GB SSD M.2 PCIE (1 slot)",
        "Card":"NVIDIA GeForce MX450 2GB GDDR5 + Intel Iris Xe Graphics",
        "screen":"15.6 inch FHD (1920 x 1080) IPS, micro-edge, BrightView, 250 nits, 45% NTSC",
        "CGT": "1x SuperSpeed USB Type-C® 10Gbps signaling rate (USB Power Delivery, DisplayPort™ 1.4, HP Sleep and Charge)/2x SuperSpeed USB Type-A 5Gbps signaling rate/1x HDMI 2.0/1x headphone&microphone combo/1 x AC smart pin",
        "keyboard":"Không LED",
        "SDcard":"multi-format SD media card reader",
        "Audio":"B&O, Dual Speakers, HP Audio Boost",
        "Bluetooth":"v5.0",        
        "Webcam":"HP Wide Vision HD Camera",
        "OS":"Windows 11",
        "Pin":"3 Cell 41WHr",
        "Weigth":"1.75 kg",
        "color":"Natural silver",
        "size":"36.02 x 23.4 x 1.79 cm",
        "description_1":"Đánh giá chi tiết laptop HP Pavilion 15 EG0506TX 46M05PA/Laptop HP Pavilion 15 EG0506TX 46M05PA là mẫu laptop cho sinh viên, nhân viên văn phòng tầm trung rất được chú ý bởi thiết kế và hiệu năng mạnh mẽ của mình.",
        "description_2":"Thiết kế mỏng nhẹ, sang trọng, đẹp mắt/Laptop HP Pavilion 15 EG0506TX 46M05PA có kích thước màn hình 15.6 inch, độ dày chỉ 17.9 mm và cân nặng 1.75 kg. Với kích thước mỏng nhẹ này bạn hoàn toàn có thể cầm máy bằng 1 tay dễ dàng, phù hợp với những ai thường xuyên thay đổi vị trí làm việc./Máy được thiết kế với phong cách tối giản màu Natural silver, với logo HP sáng bóng đính giữa trung tâm mặt A (mặt trên) tạo điểm nhấn ấn tượng cho HP Pavilion 15 EG0506TX 46M05PA.",
        "description_3":"Cấu hình tối ưu hóa cho công việc/Là mẫu laptop tầm trung, laptop HP Pavilion 15 EG0506TX 46M05PA được trang bị CPU Intel Core i5-1135G7, card đồ họa NVIDIA GeForce MX450 2GB GDDR5 + Intel Iris Xe Graphics mạnh mẽ. Đảm bảo các tác vụ công việc được hoạt động mượt mà, ổn định, các phần mềm đồ họa cũng không là vấn đề quá lớn./Bên cạnh đó máy các tựa game cơ bản như Liên Minh Huyền Thoại và Fifa Online 4, Dota 2,… cho đến các tựa game AAA đồ họa cao cũng không thể làm khó được mẫu laptop HP tầm trung này.",
        "description_4":"Màn hình IPS Full HD/Màn hình 15.6 inch FHD (1920 x 1080) IPS, micro-edge, BrightView, 250 nits, 45% NTSC được trang bị trên laptop HP Pavilion 15 EG0506TX 46M05PA. Với độ phủ màu ở mức khá và độ sáng ở mức 250 nits đảm bảo chất lượng hình ảnh sống động, sắc nét, thỏa mãn nhu cầu giải trí cơ bản của người dùng.",
        "description_5":"Bàn phím cứng cáp, độ nảy cao/Bàn phím của HP Pavilion 15 EG0506TX 46M05PA có thiết kế khá dày, cứng chắc, độ lún thấp và độ nảy cao giúp tạo cảm giác gõ phím nhanh hơn và chính xác hơn. Phần bàn phím chính và phím số phụ có kích thước khá lớn, phù hợp với những ai thường xuyên soạn thảo văn bản./Với những gì mà mình sở hữu, laptop HP Pavilion 15 EG0506TX 46M05PA chắc chắn là mẫu laptop văn phòng bạn không nên bỏ qua.",
        "description_6":"",
        "old-price":19990000,
        "new-price":19590000
    },
    {
        "productId": 20007, 
        "brand": "HP", 
        "img_1":"image/product/20007_1.png",
        "img_2":"image/product/20007_2.png",
        "img_3":"image/product/20007_3.png",
        "img_4":"image/product/20007_4.png",
        "img_5":"image/product/20007_5.png",
        "img_6":"image/product/20007_6.png",
        "name": "Laptop HP ProBook 450 G8 614K3PA",
        "CPU": "Intel Core i5-1135G7 2.4GHz up to 4.2GHz 8MB",
        "RAM":"8GB DDR4 3200MHz (2x SO-DIMM socket, up to 32GB SDRAM)", 
        "Hardware": "512GB SSD M.2 PCIE",
        "Card":"Intel Iris Xᵉ Graphics",
        "screen":"15.6 inch FHD (1920 x 1080) Diagonal IPS Anti-Glare WLED-Backlit, 45% NTSC, 250nits",
        "CGT": "1x USB 3.1 Gen 2 Type-C port/3x USB 3.1 Gen 1 Type-A ports (1 Charging, 1 Powered port)/1x HDMI 1.4b/1x headphone&microphone combo/1x RJ-45 (Ethernet) port/1x AC power port/FingerPrint",
        "keyboard":"Không LED",
        "SDcard":"SD Card Reader (Supports SD, SDHC, SDXC)",
        "Audio":"2 Integrated Stereo Speakers",
        "Bluetooth":"v5.0",        
        "Webcam":"720p HD Camera",
        "OS":"Windows 11 Home",
        "Pin":"3 Cell 45WHr",
        "Weigth":"1.74kg",
        "color":"Bạc",
        "size":"35,94 x 23,39 x 1,99 cm",
        "description_1":"Đánh giá chi tiết laptop HP ProBook 450 G8 614K3PA",
        "description_2":"Thiết kế sang trọng/Laptop có kiểu dáng bắt mắt với thân máy siêu mỏng, hoàn thiện từ vỏ nhôm nguyên khối sang trọng. Phiên bản màu bạc thời trang, logo HP nổi bật bóng bẩy cùng viền màn hình mỏng hai cạnh thể hiện sự hiện đại và thời thượng. Tuy mỏng nhẹ nhưng chiếc máy này bền bỉ với khả năng chống sốc và chống va đập tối ưu, sử dụng được trong thời gian lâu dài.",
        "description_3":"Màn hình lớn 15.6 inch Full HD/Trang bị màn hình 15.6 inch với độ phân giải Full HD sắc nét mang đến những hình ảnh rõ nét, nâng tầm trải nghiệm xem và bảo vệ mắt tốt hơn. Với thiết kế mỏng ở hai cạnh bên, hiển thị hấp dẫn, đồng thời giúp kích thước tổng thể gọn gàng hơn đáng kể./Ngoài ra với IPS anti-glare mang lại khả năng chống chói, giúp người dùng có thể yên tâm sử dụng trong điều kiện ánh sáng mạnh.",
        "description_4":"Sức mạnh hiệu năng khủng/Sở hữu cấu hình đáng kinh ngạc trên nhờ bộ vi xử lý AMD Ryzen™ 7-4700U mnag tới sức mạnh giúp người dùng chạy tốt mọi tác vụ dù công việc hay giải trí. Đồng thời với 8GB DDR4-3200Mhz SDRAM và 512 GB PCIe® NVMe™ M.2 SSD giúp máy chạy đa nhiệm mượt mà, tốc độ mở ứng dụng cực nhanh./Trang bị sẵn card đồ họa AMD Radeon™ Graphics hỗ trợ những công việc liên quan đến đồ họa, xử lý hình ảnh, chỉnh sửa video và cả chơi game tốt hơn. Hoàn thành tốt các tác vụ chỉnh sửa hình ảnh, đồ họa, dựng video cơ bản hay thậm chí là làm hiệu ứng ở mức độ không quá phức tạp.",
        "description_5":"Tính bảo mật cao/Bạn có thể đăng nhập một cách dễ dàng bằng 1 cái chạm ngón tay và đảm bảo dữ liệu được bảo mật an toàn./Đặc biệt cơ chế bảo mật  cũng được chú trọng hơn khi HP cung cấp sẵn bộ Client Security Suite Gen3, phù hợp với doanh nghiệp nhỏ không có bộ phận IT chuyên biệt. Bên cạnh đó, công nghệ SureStart nhằm bảo vệ và phục hồi BIOS về trạng thái ban đầu trong trường hợp bị tấn công.",
        "description_6":"Bàn phím hỗ trợ làm việc tốt/Diện tích bề mặt phím lớn, độ nảy tốt và hành trình phím hợp lý, phù hợp cho người dùng phải làm việc với văn bản dài hoặc trả lời email hằng ngày. Ngoài ra, tích hợp đèn nên bàn phím giúp sử dụng trong điện kiện thiếu ánh sáng./Touchpad kích thước tương đối rộng, 2 phím nhấn chuột trái/phải được làm chìm xuống càng làm tăng thêm sự thoải mái của người dùng khi rê tay.",
        "old-price":20990000,
        "new-price":19990000
    },
    {
        "productId": 20008, 
        "brand": "HP", 
        "img_1":"image/product/20008_1.png",
        "img_2":"image/product/20008_2.png",
        "img_3":"image/product/20008_3.png",
        "img_4":"image/product/20008_4.png",
        "img_5":"image/product/20008_5.png",
        "img_6":"image/product/20008_6.png",
        "name": "Laptop HP Pavilion 14 dv2032TU 6K768PA",
        "CPU": "Intel Core i7-1255U 1.7GHz up to 4.7GHz 12MB",
        "RAM":"8GB (4x2) DDR4 3200MHz (2x SO-DIMM socket, up to 16GB SDRAM)", 
        "Hardware": "512GB PCIe NVMe M.2 SSD (1 slot)",
        "Card":"Intel Iris Xe Graphics",
        "screen":"14 inch FHD (1920 x 1080) IPS, micro-edge, BrightView, 250 nits, 45% NTSC",
        "CGT": "1x SuperSpeed USB Type-C 10Gbps signaling rate (USB Power Delivery, DisplayPort 1.4, HP Sleep and Charge)/2x SuperSpeed USB Type-A 5Gbps signaling rate/1x HDMI 2.1/1x headphone&microphone combo/1x AC smart pin",
        "keyboard":"Không LED",
        "SDcard":"None",
        "Audio":"B&O PLAY; HP Audio Boost; Dual speakers",
        "Bluetooth":"v5.2",        
        "Webcam":"HP Wide Vision 720p HD camera with temporal noise reduction and integrated dual array digital microphones",
        "OS":"Windows 11 Home",
        "Pin":"3 Cell 43WHr",
        "Weigth":"1.41 kg",
        "color":"Warm Gold",
        "size":"32.5 x 21.66 x 1.7 cm",
        "description_1":"Đánh giá chi tiết HP Pavilion 14 dv2032TU 6K768PA/Laptop HP Pavilion 14 dv2032TU 6K768PA là một chiếc laptop văn phòng mang vẻ đẹp hút mắt và tạo ấn tượng đối với khách hàng. Thiết kế trong từng chi tiết máy tính đều được trau chuốt và sắp đặt kĩ lượng để bộc lộ hết vẻ đẹp hiện đại và thời thượng của laptop.",
        "description_2":"Thiết kế đẹp và tiện lợi/HP Pavilion 14 dv2032TU 6K768PA khoác lên mình màu áo vàng gold hiện đại và thanh lịch, một màu sắc nhẹ nhàng, ấm áp và tinh tế. Viền màn hình cũng được thiết kế siêu mỏng, sang trọng, càng thể hiện được nét đẹp thanh thoát của sản phẩm./Đặc biệt, HP còn rất tinh tế trong việc đem đến trải nghiệm tốt nhất cho người dùng. Nhiều chi tiết nhỏ được gia công tỉ mỉ nhưng mang lại giá trị sử dụng cao, cho phép người dùng làm việc thuận tiện hơn. Ví dụ như phần bản lề được nâng lên một góc thích hợp để bạn có thể gõ phím thoải mái hơn cũng như nâng cao khả năng tản nhiệt của laptop.",
        "description_3":"Hiệu năng HP Pavilion 14 bền bỉ và mượt mà/HP Pavilion 14 dv2032TU 6K768PA là một trong những mẫu laptop mỏng nhẹ sở hữu sức mạnh khủng hiện nay. Nó cho thấy được sự cân bằng và hài hòa giữa hiệu năng cũng như ngoại hình bên ngoài. Không chỉ sở hữu vẻ ngoài đẹp ấn tượng mà HP Pavilion 14 còn có thể đáp ứng được nhu cầu sử dụng của nhiều đối tượng khách hàng từ học sinh, sinh viên đến nhân viên văn phòng./Được trang bị bộ vi xử lý thế hệ 12 mạnh mẽ, sẽ không để bạn chờ đợi lâu khi xử lý các tác vụ. Kết hợp với bộ nhớ RAM dung lượng 8GB chuẩn DDR4, ổ cứng 512GB PCIe NVMe SSD giúp xử lý các tác vụ một cách mượt mà và nhanh chóng, tăng tốc quá trình truy cập và đảm bảo sự ổn định khi sử dụng.",
        "description_4":"Dung lượng pin lớn và hỗ trợ sạc nhanh/HP Pavilion 14 được trang bị viên pin 43WHr, đủ lớn để bạn làm việc và học tập cả ngày dài. Hơn nữa, công nghệ sạc pin nhanh cho phép bạn đầy 90% trong vòng 90 phút. Điều này không những tăng tính cơ động cho máy, mà nó còn giúp bạn thoải mái sử dụng laptop ở bất cứ nơi nào.",
        "description_5":"Chất lượng âm thanh tuyệt vời/Chưa dừng lại ở đó khi HP Pavilion 14 dv2032TU 6K768PA cũng được trang bị hệ thống loa kép cùng công nghệ khuếch âm HP Audio Boost cùng âm thanh được tinh chỉnh bởi các chuyên gia của B&O PLAY./Sự kết hợp này đang đem đến cho người dùng trải nghiệm âm nhạc với chiều sâu chân thực và đầy sống động. Do đó, dù ở vị trí nào thì chất lượng âm thanh sẽ không bị ảnh hưởng hay khác biệt nhiều.",
        "description_6":"Khả năng hiển thị sống động/Sở hữu kích thước màn hình 14 inch với độ phân giải Full HD cùng tấm nền IPS giúp hình ảnh và màu sắc hiển thị vô cùng sắc nét, chân thực và sống động. Không gian hiển thị cũng được mở rộng hơn nhờ thiết kế tràn viền, nó mang đến hình ảnh sống động đến từng chi tiết nhỏ và mọi góc nhìn./Laptop HP Pavilion 14 mang thiết kế nhỏ gọn, tối giản với đường nét góc cạnh tỉ mỉ và tinh tế. Trọng lượng thiết bị được tối ưu hoá chỉ 1,4kg để người dùng có thể linh hoạt hơn trong việc mang xách, di chuyển đến bất kỳ đâu.",
        "price":21490000
    },
    {
        "productId": 20009, 
        "brand": "HP", 
        "img_1":"image/product/20009_1.png",
        "img_2":"image/product/20009_2.png",
        "img_3":"image/product/20009_3.png",
        "img_4":"image/product/20009_4.png",
        "img_5":"image/product/20009_5.png",
        "img_6":"image/product/20009_6.png",
        "name": "Laptop HP Envy 13 BA1536TU 4U6M5PA",
        "CPU": "Intel Core i5-1135G7 2.4GHz up to 4.2GHz 8MB",
        "RAM":"8GB DDR4 3200MHz (Onboard)", 
        "Hardware": "512GB PCIe NVMe M.2 SSD",
        "Card":"Intel Iris Xe Graphics",
        "screen":"13.3 inch FHD (1920 x 1080) IPS with 100% sRGB, BrightView Micro-Edge, 400 nits ",
        "CGT": "2 x SuperSpeed USB Type-A 5Gbps signaling rate/1 x Jack tai nghe 3.5 mm/1 x Thunderbolt 4 USB-C",
        "keyboard":"Không LED",
        "SDcard":"MicroSD Media Card Reader",
        "Audio":"Bang & Olufsen, Dual speakers, HP Audio Boost",
        "Bluetooth":"v5.0",        
        "Webcam":"HP Wide Vision HD Camera",
        "OS":"Windows 11 Home",
        "Pin":"3 Cell 51WHr",
        "Weigth":"1.3 kg",
        "color":"Pale Gold",
        "size":"30.65 x 19.46 x 1.69 cm",
        "description_1":"Đánh giá chi tiết laptop HP Envy 13 BA1536TU 4U6M5PA/Laptop HP Envy 13 BA1536TU 4U6M5PA ra mắt vào năm 2021, là một gương mặt mới trong làng laptop văn phòng trứ danh của nhà HP. Envy 13 BA1536TU sở hữu một thiết kế trẻ trung, năng động chắc chắn sẽ mang đến cho bạn sự tự tin nhất khi cầm trên tay. Đây là chiếc laptop kết hợp hoàn hảo của một chiếc laptop văn phòng với thời trang hiện đại.",
        "description_2":"Thiết kế Envy 13 BA1536TU nổi bật/Envy 13 BA1536TU được thiết kế theo ngôn ngữ xu hướng chuẩn hiện đại. Nó cũng tương tự như các dòng laptop ultrabook hiện nay với kích thước mỏng hơn và nhẹ mang lại cảm giác thanh thoát và sang trọng cho người dùng. Laptop được gia công hoàn toàn bằng kim loại màu vàng ánh kim sang trọng, toát lên vẻ chuyên nghiệp cho bạn khi sử dụng.",
        "description_3":"Cấu hình khủng/HP Envy 13 BA1536TU sở hữu CPU Intel Core i5-1135G7 thế hệ mới nhất với xung nhịp 4.20GHz, bạn có thể xử lý mượt các tác vụ hằng ngày như làm việc văn phòng, xem phim, lướt web và chơi các tựa game phổ biến một cách mượt mà và trơn tru./Bên cạnh đó, HP còn trang bị cho Envy 13 BA1536TU một ổ cứng tiêu chuẩn nhất với 8GB RAM DDR4 và 512GB PCIe NVMe M.2 dung lượng SSD để cung cấp cho người dùng trải nghiệm đa nhiệm mượt mà, lưu trữ dữ liệu thoải mái và tốc độ truyền tải nhanh chóng.",
        "description_4":"Màn hình và bàn phím/Sở hữu màn hình 13.3 inch, độ phân giải Full HD, Envy 13 BA1536TU cho chất lượng hình ảnh hiển thị cực kỳ rõ nét, sống động. Công nghệ màn hình IPS sẽ cho bạn thưởng thức những bức ảnh màu sắc tươi sáng và rực rỡ nhất mà không gây khó chịu cho mắt./HP đã nghiên cứu và trang bị bàn phím hiện đại trên Envy 13 BA1536TU nhằm giúp người dùng có trải nghiệm sử dụng một cách tối ưu. Khoảng cách giữa các phím bấm hợp lý, độ nảy cao và hành trình phím sâu tạo cảm giác nhập liệu nhanh chóng và thoải mái./Ngoài ra, Touchpad cũng đã được HP cải tiến với diện tích lớn, hỗ trợ bạn sử dụng cảm ứng đa điểm để cuộn văn bản, xoay hình ảnh và nhiều thao tác dễ dàng hơn.",
        "description_5":"Cổng kết nối đa dạng/Để đáp ứng nhu cầu liên kết với các thiết bị ngoại vi, Envy 13 BA1536TU được trang bị đầy đủ các cổng kết nối như ở cạnh bên phải là jack nguồn, 2 USB 3.2 Type A và combo tai nghe/micro 3.5mm; ở cạnh trái đầy đủ hơn với HDMI 2.1, USB 3.1 Type A, Ethernet, USB 3.1 Type C và đầu đọc thẻ SD.",
        "description_6":"",
        "old-price":23990000,
        "new-price":21990000
    },
    {
        "productId": 20010, 
        "brand": "HP", 
        "img_1":"image/product/20010_1.png",
        "img_2":"image/product/20010_2.png",
        "img_3":"image/product/20010_3.png",
        "img_4":"image/product/20010_4.png",
        "img_5":"image/product/20010_5.png",
        "img_6":"image/product/20010_6.png",
        "name": "Laptop HP Spectre x360 14 ef0030TU 6K773PA",
        "CPU": "Intel Core i7-1255U 1.7GHz up to 4.7GHz 12MB",
        "RAM":"16GB LPDDR4x 4266MHz (Onboard)", 
        "Hardware": "1TB PCIe NVMe TLC M.2 SSD",
        "Card":"Intel Iris Xe Graphics",
        "screen":"13.5 inch 3K2K (3000 x 2000), OLED, multitouch-enabled, UWVA, edge-to-edge glass, micro-edge, anti-reflection Corning Gorilla Glass NBT, Low Blue Light, SDR 400 nits, HDR 500 nits, 100% DCI-P3",
        "CGT": "2x Thunderbolt 4 with USB4 Type-C 40Gbps signaling rate (USB Power Delivery, DisplayPort 1.4, HP Sleep and Charge)/1x SuperSpeed USB Type-A 10Gbps signaling rate (HP Sleep and Charge)/1x headphone&microphone combo/FingerPrint",
        "keyboard":"LED trắng",
        "SDcard":"MicroSD Media Card Reader",
        "Audio":"Bang & Olufsen, Quad Speakers, HP Audio Boost",
        "Bluetooth":"v5.0",        
        "Webcam":"HP True Vision 5MP IR camera with camera shutter, temporal noise reduction and integrated dual array digital microphones",
        "OS":"Windows 11 Home",
        "Pin":"4 Cell 66WHr",
        "Weigth":"1.36 kg",
        "color":"Nocturne blue aluminum",
        "size":"29.8 x 22.04 x 1.69 cm",
        "description_1":"Đánh giá chi tiết laptop HP Spectre x360 14 ef0030TU 6K773P/Được đánh giá là một trong những phân khúc cao cấp của dòng laptop văn phòng, laptop HP Spectre luôn được người dùng tin dùng khi muốn tìm kiếm một chiếc laptop cao cấp để phục vụ nhu cầu sử dụng của mình. Và một lần nữa HP Spectre x360 14 ef0030TU 6K773PA không làm người dùng thất vọng khi có thể tiếp nối mọi đặc điểm nổi bật của những người anh em tiền nhiệm.",
        "description_2":"Thiết kế ấn tượng/Laptop HP Spectre x360 sở hữu ngôn ngữ thiết kế vô cùng hiện đại, thanh lịch và cực kỳ sang trọng với những đường bo cong mềm mại. Khoác lên mình bộ áo xanh độc đáo, HP Spectre x360 hầu như phù hợp với mọi người dùng từ nam đến nữ. Được hoàn thiện bằng chất liệu nhôm nguyên khối, nó không những mang tới một vẻ ngoài cao cấp và sang trọng hơn, mà còn tối ưu hóa khả năng tản nhiệt của laptop./Nhắm đến đối tượng người dùng cao cấp và yêu cầu tính di động cao nên không có chuyện gì lạ khi HP Spectre x360 sở hữu trọng lượng khá nhẹ, chỉ hơn 1,36kg để đồng hành với bạn đi đến bất cứ đâu. Hơn nữa, phần bản lề laptop còn được gấp gọn 360 độ, bạn có thể sử dụng laptop như một máy tính bảng, linh hoạt phục vụ công việc.",
        "description_3":"Màn hình hiển thị siêu sắc nét/Sở hữu kích thước màn hình 13.5 inch, độ phân giải 3000x2000 dưới tấm nền OLED siêu ấn tượng, HP Spectre x360 sẽ mang đến cho bạn trải nghiệm hình ảnh vô cùng sắc nét, sống động và chân thật. Có thể nói đây là kích thước laptop rất được ưa chuộng vì nó vừa đảm bảo tính di động vừa cung cấp một không gian hiển thị vừa đủ để bạn làm việc./Vì bạn có thể gấp gọn laptop và sử dụng như một máy tính bảng nên màn hình HP Spectre x360 là màn hình cảm ứng. Độ phủ màu 100% DCI-P3, độ sáng màn hình 500 nits và cảm ứng đa điểm giúp nâng cao hiệu quả công việc và mang đến cho bạn trải nghiệm sử dụng đỉnh cao mà hầu như bạn không thể tìm đâu ở một dòng sản phẩm nào khác.",
        "description_4":"Hiệu năng HP Spectre x360 siêu khủng/Không chỉ sở hữu vẻ ngoài thu hút, hiệu năng của HP Spectre x360 cũng không phải dạng vừa đâu. Laptop được trang bị con chip Intel Core i7 gen 12th thế hệ mới nhất cung cấp sức mạnh siêu khủng có thể so sánh ngang bằng với nhiều máy tính để bàn. Kết hợp với đó là card đồ họa tích hợp giúp máy xử lý mọi tác vụ một cách nhanh chóng./Kết hợp với đó, 16GB RAM và 1TB SSD giúp laptop chạy đa nhiệm mượt mà, bạn có thể mở nhiều tab và chạy nhiều ứng dụng cùng một lúc. Ổ cứng dung lượng lớn để bạn thoải mái cài hệ điều hành cũng như lưu trữ các ứng dụng mà không phải lo lắng thiếu hay cần nâng cấp thêm dung lượng. ",
        "description_5":"Bàn phím và touchpadVì thuộc phân khúc laptop văn phòng nên trải nghiệm gõ phím luôn được hãng quan tâm và chau chuốt kỹ lưỡng. Layout bàn phím rõ ràng, khoảng cách giữa các phím hợp lý, hành trình phím sâu và độ nảy tốt mang lại cảm giác gõ phím thoải mái, hạn chế tình trạng đau mỏi tay khi gõ phím quá lâu./Touchpad cũng được nâng cấp rõ rệt khi diện tích được mở rộng hơn. Được phủ một lớp nhám mịn giúp cho việc thao tác di chuột của bạn luôn được chuẩn xác không thua kém gì so với những chuột máy tính rời thông thường. Nhờ công nghệ cảm ứng đa điểm, bạn có thể thoải mái thao tác với 2 hoặc nhiều ngón để thực hiện nhiều tổ hợp thao tác, tăng cường hiệu quả sử dụng laptop.",
        "description_6":"Cổng kết nối đa dạng/Dù sở hữu ngoại hình vô cùng mỏng, nhẹ nhưng HP Spectre x360 vẫn còn rất khéo léo khi trang bị đầy đủ cổng kết nối đa dạng như cổng Thunderbolt, USB Type C, USB Type A và jack cắm tai nghe 3.5mm,...để bạn có thể thoải mái kết nối với nhiều thiết bị ngoại vi, nâng cao trải nghiệm của người dùng.",
        "price":51990000
    }
]